django_sql_test/__init__.py
django_sql_test/app_settings.py
django_sql_test/diff_utils.py
django_sql_test/engine.py
django_sql_test/utils.py
django_sql_test-0.3.0.dist-info/LICENSE
django_sql_test-0.3.0.dist-info/METADATA
django_sql_test-0.3.0.dist-info/WHEEL
django_sql_test-0.3.0.dist-info/RECORD
