Metadata-Version: 2.3
Name: django-sql-test
Version: 0.3.0
Summary: A Django test mixin that captures and displays SQL query diffs between test runs, helping to track database-related changes in your tests.
License: MIT
Author: Denis Zalivin
Author-email: zalivindenis@gmail.com
Requires-Python: <4.0,>=3.9
Classifier: Development Status :: 4 - Beta
Classifier: Framework :: Django
Classifier: Framework :: Django :: 4
Classifier: Framework :: Django :: 4.0
Classifier: Framework :: Django :: 4.1
Classifier: Framework :: Django :: 4.2
Classifier: Framework :: Django :: 5
Classifier: Framework :: Django :: 5.0
Classifier: Framework :: Django :: 5.1
Classifier: Framework :: Django :: 5.2
Classifier: Intended Audience :: Developers
Classifier: License :: OSI Approved :: MIT License
Classifier: Operating System :: OS Independent
Classifier: Programming Language :: Python :: 3
Classifier: Programming Language :: Python :: 3.9
Classifier: Programming Language :: Python :: 3.10
Classifier: Programming Language :: Python :: 3.11
Classifier: Programming Language :: Python :: 3.12
Classifier: Programming Language :: Python :: 3.13
Classifier: Topic :: Software Development :: Testing
Requires-Dist: django (>=4.0,<6.0)
Requires-Dist: sql-metadata (>=2.15.0,<3.0.0)
Project-URL: Homepage, https://github.com/shaihulud/django-sql-test
Project-URL: Repository, https://github.com/shaihulud/django-sql-test
Project-URL: issues, https://github.com/shaihulud/django-sql-test/issues
